dupcomposer/__init__.py
dupcomposer/__main__.py
dupcomposer/backup_config.py
dupcomposer/backup_keyring.py
dupcomposer/backup_runner.py
dup_composer-0.3.1.dist-info/LICENSE
dup_composer-0.3.1.dist-info/METADATA
dup_composer-0.3.1.dist-info/WHEEL
dup_composer-0.3.1.dist-info/entry_points.txt
dup_composer-0.3.1.dist-info/top_level.txt
dup_composer-0.3.1.dist-info/RECORD
