Metadata-Version: 2.1
Name: dup-composer
Version: 0.3.1
Summary: Dup-composer is a front-end script for Duplicity, that lets you define your backups in a configuration file and execute them in a simple way.
Home-page: https://github.com/cruizer/dup-composer
Author: Tamas Kalman
Author-email: hello@tamaskalman.com
License: MIT
Platform: UNKNOWN
Classifier: Development Status :: 3 - Alpha
Classifier: Environment :: Console
Classifier: Operating System :: POSIX :: Linux
Classifier: Programming Language :: Python :: 3.7
Classifier: Topic :: System :: Archiving :: Backup
Requires-Dist: keyring (>=19.2.0)
Requires-Dist: SecretStorage (>=3.1.1)
Requires-Dist: PyYAML (>=5.1)
